odoo/addons/github_connector_odoo/README.rst
odoo/addons/github_connector_odoo/__init__.py
odoo/addons/github_connector_odoo/__manifest__.py
odoo/addons/github_connector_odoo/monkeypatching.py
odoo/addons/github_connector_odoo/data/function.xml
odoo/addons/github_connector_odoo/data/ir_cron.xml
odoo/addons/github_connector_odoo/data/oca.png
odoo/addons/github_connector_odoo/data/odoo_category_data.xml
odoo/addons/github_connector_odoo/data/odoo_licence.xml
odoo/addons/github_connector_odoo/data/odoo_manifest_key_data.xml
odoo/addons/github_connector_odoo/demo/github_analysis_rule_demo.xml
odoo/addons/github_connector_odoo/demo/github_analysis_rule_group_demo.xml
odoo/addons/github_connector_odoo/demo/github_organization.xml
odoo/addons/github_connector_odoo/i18n/es.po
odoo/addons/github_connector_odoo/i18n/github_connector_odoo.pot
odoo/addons/github_connector_odoo/i18n/it.po
odoo/addons/github_connector_odoo/models/__init__.py
odoo/addons/github_connector_odoo/models/abstract_action_mixin.py
odoo/addons/github_connector_odoo/models/github_analysis_rule.py
odoo/addons/github_connector_odoo/models/github_organization.py
odoo/addons/github_connector_odoo/models/github_repository.py
odoo/addons/github_connector_odoo/models/github_repository_branch.py
odoo/addons/github_connector_odoo/models/odoo_author.py
odoo/addons/github_connector_odoo/models/odoo_category.py
odoo/addons/github_connector_odoo/models/odoo_lib_bin.py
odoo/addons/github_connector_odoo/models/odoo_lib_python.py
odoo/addons/github_connector_odoo/models/odoo_license.py
odoo/addons/github_connector_odoo/models/odoo_manifest_key.py
odoo/addons/github_connector_odoo/models/odoo_module.py
odoo/addons/github_connector_odoo/models/odoo_module_version.py
odoo/addons/github_connector_odoo/readme/CONFIGURE.md
odoo/addons/github_connector_odoo/readme/CONTRIBUTORS.md
odoo/addons/github_connector_odoo/readme/DESCRIPTION.md
odoo/addons/github_connector_odoo/readme/ROADMAP.md
odoo_addon_github_connector_odoo-18.0.1.0.1.1.dist-info/METADATA
odoo_addon_github_connector_odoo-18.0.1.0.1.1.dist-info/WHEEL
odoo_addon_github_connector_odoo-18.0.1.0.1.1.dist-info/top_level.txt
odoo_addon_github_connector_odoo-18.0.1.0.1.1.dist-info/RECORD
