Metadata-Version: 2.1
Name: odoo-addon-github_connector_odoo
Version: 18.0.1.0.1.1
Requires-Python: >=3.10
Requires-Dist: odoo-addon-github_connector==18.0.*
Requires-Dist: odoo==18.0.*
Requires-Dist: pathspec
Summary: Analyze Odoo modules information from Github repositories
Home-page: https://github.com/OCA/interface-github
License: AGPL-3
Author: Odoo Community Association (OCA), Sylvain LE GAL, GRAP
Author-email: support@odoo-community.org
Classifier: Programming Language :: Python
Classifier: Framework :: Odoo
Classifier: Framework :: Odoo :: 18.0
Classifier: License :: OSI Approved :: GNU Affero General Public License v3
